<?xml version="1.0" encoding="UTF-8"?>
<sbml xmlns="http://www.sbml.org/sbml/level3/version1/core" level="3" version="1">
  <model metaid="pathway" id="pathway">
    <listOfFunctionDefinitions>
      <functionDefinition id="rate_law_one_s_one_p">
        <math xmlns="http://www.w3.org/1998/Math/MathML">
          <lambda>
            <bvar>
              <ci> E_conc </ci>
            </bvar>
            <bvar>
              <ci> k_cat </ci>
            </bvar>
            <bvar>
              <ci> conc_S </ci>
            </bvar>
            <bvar>
              <ci> conc_P </ci>
            </bvar>
            <bvar>
              <ci> k_S </ci>
            </bvar>
            <bvar>
              <ci> k_P </ci>
            </bvar>
            <bvar>
              <ci> dG0 </ci>
            </bvar>
            <bvar>
              <ci> R </ci>
            </bvar>
            <bvar>
              <ci> T </ci>
            </bvar>
            <apply>
              <divide/>
              <apply>
                <times/>
                <ci> E_conc </ci>
                <ci> k_cat </ci>
                <apply>
                  <divide/>
                  <ci> conc_S </ci>
                  <ci> k_S </ci>
                </apply>
                <apply>
                  <minus/>
                  <cn type="integer"> 1 </cn>
                  <apply>
                    <divide/>
                    <apply>
                      <divide/>
                      <ci> conc_P </ci>
                      <ci> conc_S </ci>
                    </apply>
                    <apply>
                      <exp/>
                      <apply>
                        <divide/>
                        <apply>
                          <minus/>
                          <ci> dG0 </ci>
                        </apply>
                        <apply>
                          <times/>
                          <ci> R </ci>
                          <ci> T </ci>
                        </apply>
                      </apply>
                    </apply>
                  </apply>
                </apply>
              </apply>
              <apply>
                <plus/>
                <cn type="integer"> 1 </cn>
                <apply>
                  <divide/>
                  <ci> conc_S </ci>
                  <ci> k_S </ci>
                </apply>
                <apply>
                  <divide/>
                  <ci> conc_P </ci>
                  <ci> k_P </ci>
                </apply>
              </apply>
            </apply>
          </lambda>
        </math>
      </functionDefinition>
      <functionDefinition id="rate_law_two_s_one_p">
        <math xmlns="http://www.w3.org/1998/Math/MathML">
          <lambda>
            <bvar>
              <ci> E_conc </ci>
            </bvar>
            <bvar>
              <ci> k_cat </ci>
            </bvar>
            <bvar>
              <ci> conc_S1 </ci>
            </bvar>
            <bvar>
              <ci> conc_S2 </ci>
            </bvar>
            <bvar>
              <ci> conc_P </ci>
            </bvar>
            <bvar>
              <ci> k_S1 </ci>
            </bvar>
            <bvar>
              <ci> k_S2 </ci>
            </bvar>
            <bvar>
              <ci> k_P </ci>
            </bvar>
            <bvar>
              <ci> dG0 </ci>
            </bvar>
            <bvar>
              <ci> R </ci>
            </bvar>
            <bvar>
              <ci> T </ci>
            </bvar>
            <apply>
              <divide/>
              <apply>
                <times/>
                <ci> E_conc </ci>
                <ci> k_cat </ci>
                <apply>
                  <divide/>
                  <ci> conc_S1 </ci>
                  <ci> k_S1 </ci>
                </apply>
                <apply>
                  <divide/>
                  <ci> conc_S2 </ci>
                  <ci> k_S2 </ci>
                </apply>
                <apply>
                  <minus/>
                  <cn type="integer"> 1 </cn>
                  <apply>
                    <divide/>
                    <apply>
                      <divide/>
                      <ci> conc_P </ci>
                      <apply>
                        <times/>
                        <ci> conc_S1 </ci>
                        <ci> conc_S2 </ci>
                      </apply>
                    </apply>
                    <apply>
                      <exp/>
                      <apply>
                        <divide/>
                        <apply>
                          <minus/>
                          <ci> dG0 </ci>
                        </apply>
                        <apply>
                          <times/>
                          <ci> R </ci>
                          <ci> T </ci>
                        </apply>
                      </apply>
                    </apply>
                  </apply>
                </apply>
              </apply>
              <apply>
                <plus/>
                <cn type="integer"> 1 </cn>
                <apply>
                  <divide/>
                  <ci> conc_S1 </ci>
                  <ci> k_S1 </ci>
                </apply>
                <apply>
                  <divide/>
                  <ci> conc_S2 </ci>
                  <ci> k_S2 </ci>
                </apply>
                <apply>
                  <divide/>
                  <ci> conc_P </ci>
                  <ci> k_P </ci>
                </apply>
              </apply>
            </apply>
          </lambda>
        </math>
      </functionDefinition>
      <functionDefinition id="rate_law_one_s_two_p">
        <math xmlns="http://www.w3.org/1998/Math/MathML">
          <lambda>
            <bvar>
              <ci> E_conc </ci>
            </bvar>
            <bvar>
              <ci> k_cat </ci>
            </bvar>
            <bvar>
              <ci> conc_S </ci>
            </bvar>
            <bvar>
              <ci> conc_P1 </ci>
            </bvar>
            <bvar>
              <ci> conc_P2 </ci>
            </bvar>
            <bvar>
              <ci> k_S </ci>
            </bvar>
            <bvar>
              <ci> k_P1 </ci>
            </bvar>
            <bvar>
              <ci> k_P2 </ci>
            </bvar>
            <bvar>
              <ci> dG0 </ci>
            </bvar>
            <bvar>
              <ci> R </ci>
            </bvar>
            <bvar>
              <ci> T </ci>
            </bvar>
            <apply>
              <divide/>
              <apply>
                <times/>
                <ci> E_conc </ci>
                <ci> k_cat </ci>
                <apply>
                  <divide/>
                  <ci> conc_S </ci>
                  <ci> k_S </ci>
                </apply>
                <apply>
                  <minus/>
                  <cn type="integer"> 1 </cn>
                  <apply>
                    <divide/>
                    <apply>
                      <divide/>
                      <apply>
                        <times/>
                        <ci> conc_P1 </ci>
                        <ci> conc_P2 </ci>
                      </apply>
                      <ci> conc_S </ci>
                    </apply>
                    <apply>
                      <exp/>
                      <apply>
                        <divide/>
                        <apply>
                          <minus/>
                          <ci> dG0 </ci>
                        </apply>
                        <apply>
                          <times/>
                          <ci> R </ci>
                          <ci> T </ci>
                        </apply>
                      </apply>
                    </apply>
                  </apply>
                </apply>
              </apply>
              <apply>
                <plus/>
                <cn type="integer"> 1 </cn>
                <apply>
                  <divide/>
                  <ci> conc_S </ci>
                  <ci> k_S </ci>
                </apply>
                <apply>
                  <divide/>
                  <ci> conc_P1 </ci>
                  <ci> k_P1 </ci>
                </apply>
                <apply>
                  <divide/>
                  <ci> conc_P2 </ci>
                  <ci> k_P2 </ci>
                </apply>
              </apply>
            </apply>
          </lambda>
        </math>
      </functionDefinition>
    </listOfFunctionDefinitions>
    <listOfCompartments>
      <compartment sboTerm="SBO:0000410" id="default_compartment" spatialDimensions="3" size="1" constant="true"/>
    </listOfCompartments>
    <listOfSpecies>
      <species id="Sex" compartment="default_compartment" initialConcentration="4" hasOnlySubstanceUnits="true" boundaryCondition="true" constant="false"/>
      <species id="S" compartment="default_compartment" initialConcentration="1e-05" hasOnlySubstanceUnits="true" boundaryCondition="false" constant="false"/>
      <species id="A" compartment="default_compartment" initialConcentration="1e-05" hasOnlySubstanceUnits="true" boundaryCondition="false" constant="false"/>
      <species id="B" compartment="default_compartment" initialConcentration="1e-05" hasOnlySubstanceUnits="true" boundaryCondition="false" constant="false"/>
      <species id="C" compartment="default_compartment" initialConcentration="1e-05" hasOnlySubstanceUnits="true" boundaryCondition="false" constant="false"/>
      <species id="X" compartment="default_compartment" initialConcentration="1e-05" hasOnlySubstanceUnits="true" boundaryCondition="false" constant="false"/>
      <species id="P" compartment="default_compartment" initialConcentration="1e-05" hasOnlySubstanceUnits="true" boundaryCondition="false" constant="false"/>
      <species id="Pex" compartment="default_compartment" initialConcentration="1e-05" hasOnlySubstanceUnits="true" boundaryCondition="false" constant="false"/>
      <species id="Bex" compartment="default_compartment" initialConcentration="1e-05" hasOnlySubstanceUnits="true" boundaryCondition="false" constant="false"/>
    </listOfSpecies>
    <listOfParameters>
      <parameter id="R" value="0.008315" constant="false"/>
      <parameter id="T" value="298" constant="false"/>
      <parameter id="E_conc_R1" value="1" constant="false"/>
      <parameter id="k_cat_R1" value="6" constant="false"/>
      <parameter id="k_Sex_R1" value="0.18" constant="false"/>
      <parameter id="k_S_R1" value="2.5" constant="false"/>
      <parameter id="dG0_R1" value="0" constant="false"/>
      <parameter id="E_conc_R2" value="1" constant="false"/>
      <parameter id="k_cat_R2" value="5" constant="false"/>
      <parameter id="k_S_R2" value="0.4" constant="false"/>
      <parameter id="k_X_R2" value="2.1" constant="false"/>
      <parameter id="k_A_R2" value="3.1" constant="false"/>
      <parameter id="dG0_R2" value="4" constant="false"/>
      <parameter id="E_conc_R3" value="1" constant="false"/>
      <parameter id="k_cat_R3" value="8" constant="false"/>
      <parameter id="k_A_R3" value="4.6" constant="false"/>
      <parameter id="k_X_R3" value="0.4" constant="false"/>
      <parameter id="k_B_R3" value="2.5" constant="false"/>
      <parameter id="dG0_R3" value="-5" constant="false"/>
      <parameter id="E_conc_R4" value="1" constant="false"/>
      <parameter id="k_cat_R4" value="9" constant="false"/>
      <parameter id="k_B_R4" value="0.5" constant="false"/>
      <parameter id="k_C_R4" value="0.9" constant="false"/>
      <parameter id="k_X_R4" value="3.1" constant="false"/>
      <parameter id="dG0_R4" value="-5" constant="false"/>
      <parameter id="E_conc_R5" value="1" constant="false"/>
      <parameter id="k_cat_R5" value="10" constant="false"/>
      <parameter id="k_C_R5" value="1.5" constant="false"/>
      <parameter id="k_X_R5" value="2.6" constant="false"/>
      <parameter id="k_P_R5" value="6.8" constant="false"/>
      <parameter id="dG0_R5" value="4" constant="false"/>
      <parameter id="E_conc_R6" value="1" constant="false"/>
      <parameter id="k_cat_R6" value="24" constant="false"/>
      <parameter id="k_P_R6" value="0.01" constant="false"/>
      <parameter id="k_Pex_R6" value="14" constant="false"/>
      <parameter id="dG0_R6" value="0" constant="false"/>
      <parameter id="E_conc_RTB" value="1" constant="false"/>
      <parameter id="k_cat_RTB" value="100000" constant="false"/>
      <parameter id="k_B_RTB" value="2" constant="false"/>
      <parameter id="k_Bex_RTB" value="2" constant="false"/>
      <parameter id="dG0_RTB" value="0" constant="false"/>
    </listOfParameters>
    <listOfRules>
      <assignmentRule variable="R">
        <math xmlns="http://www.w3.org/1998/Math/MathML">
          <cn> 0.008315 </cn>
        </math>
      </assignmentRule>
      <assignmentRule variable="T">
        <math xmlns="http://www.w3.org/1998/Math/MathML">
          <cn type="integer"> 298 </cn>
        </math>
      </assignmentRule>
      <assignmentRule variable="E_conc_R1">
        <math xmlns="http://www.w3.org/1998/Math/MathML">
          <cn type="integer"> 1 </cn>
        </math>
      </assignmentRule>
      <assignmentRule variable="k_cat_R1">
        <math xmlns="http://www.w3.org/1998/Math/MathML">
          <cn type="integer"> 6 </cn>
        </math>
      </assignmentRule>
      <assignmentRule variable="k_Sex_R1">
        <math xmlns="http://www.w3.org/1998/Math/MathML">
          <cn> 0.18 </cn>
        </math>
      </assignmentRule>
      <assignmentRule variable="k_S_R1">
        <math xmlns="http://www.w3.org/1998/Math/MathML">
          <cn> 2.5 </cn>
        </math>
      </assignmentRule>
      <assignmentRule variable="dG0_R1">
        <math xmlns="http://www.w3.org/1998/Math/MathML">
          <cn type="integer"> 0 </cn>
        </math>
      </assignmentRule>
      <assignmentRule variable="E_conc_R2">
        <math xmlns="http://www.w3.org/1998/Math/MathML">
          <cn type="integer"> 1 </cn>
        </math>
      </assignmentRule>
      <assignmentRule variable="k_cat_R2">
        <math xmlns="http://www.w3.org/1998/Math/MathML">
          <cn type="integer"> 5 </cn>
        </math>
      </assignmentRule>
      <assignmentRule variable="k_S_R2">
        <math xmlns="http://www.w3.org/1998/Math/MathML">
          <cn> 0.4 </cn>
        </math>
      </assignmentRule>
      <assignmentRule variable="k_X_R2">
        <math xmlns="http://www.w3.org/1998/Math/MathML">
          <cn> 2.1 </cn>
        </math>
      </assignmentRule>
      <assignmentRule variable="k_A_R2">
        <math xmlns="http://www.w3.org/1998/Math/MathML">
          <cn> 3.1 </cn>
        </math>
      </assignmentRule>
      <assignmentRule variable="dG0_R2">
        <math xmlns="http://www.w3.org/1998/Math/MathML">
          <cn type="integer"> 4 </cn>
        </math>
      </assignmentRule>
      <assignmentRule variable="E_conc_R3">
        <math xmlns="http://www.w3.org/1998/Math/MathML">
          <cn type="integer"> 1 </cn>
        </math>
      </assignmentRule>
      <assignmentRule variable="k_cat_R3">
        <math xmlns="http://www.w3.org/1998/Math/MathML">
          <cn type="integer"> 8 </cn>
        </math>
      </assignmentRule>
      <assignmentRule variable="k_A_R3">
        <math xmlns="http://www.w3.org/1998/Math/MathML">
          <cn> 4.6 </cn>
        </math>
      </assignmentRule>
      <assignmentRule variable="k_X_R3">
        <math xmlns="http://www.w3.org/1998/Math/MathML">
          <cn> 0.4 </cn>
        </math>
      </assignmentRule>
      <assignmentRule variable="k_B_R3">
        <math xmlns="http://www.w3.org/1998/Math/MathML">
          <cn> 2.5 </cn>
        </math>
      </assignmentRule>
      <assignmentRule variable="dG0_R3">
        <math xmlns="http://www.w3.org/1998/Math/MathML">
          <cn type="integer"> -5 </cn>
        </math>
      </assignmentRule>
      <assignmentRule variable="E_conc_R4">
        <math xmlns="http://www.w3.org/1998/Math/MathML">
          <cn type="integer"> 1 </cn>
        </math>
      </assignmentRule>
      <assignmentRule variable="k_cat_R4">
        <math xmlns="http://www.w3.org/1998/Math/MathML">
          <cn type="integer"> 9 </cn>
        </math>
      </assignmentRule>
      <assignmentRule variable="k_B_R4">
        <math xmlns="http://www.w3.org/1998/Math/MathML">
          <cn> 0.5 </cn>
        </math>
      </assignmentRule>
      <assignmentRule variable="k_C_R4">
        <math xmlns="http://www.w3.org/1998/Math/MathML">
          <cn> 0.9 </cn>
        </math>
      </assignmentRule>
      <assignmentRule variable="k_X_R4">
        <math xmlns="http://www.w3.org/1998/Math/MathML">
          <cn> 3.1 </cn>
        </math>
      </assignmentRule>
      <assignmentRule variable="dG0_R4">
        <math xmlns="http://www.w3.org/1998/Math/MathML">
          <cn type="integer"> -5 </cn>
        </math>
      </assignmentRule>
      <assignmentRule variable="E_conc_R5">
        <math xmlns="http://www.w3.org/1998/Math/MathML">
          <cn type="integer"> 1 </cn>
        </math>
      </assignmentRule>
      <assignmentRule variable="k_cat_R5">
        <math xmlns="http://www.w3.org/1998/Math/MathML">
          <cn type="integer"> 10 </cn>
        </math>
      </assignmentRule>
      <assignmentRule variable="k_C_R5">
        <math xmlns="http://www.w3.org/1998/Math/MathML">
          <cn> 1.5 </cn>
        </math>
      </assignmentRule>
      <assignmentRule variable="k_X_R5">
        <math xmlns="http://www.w3.org/1998/Math/MathML">
          <cn> 2.6 </cn>
        </math>
      </assignmentRule>
      <assignmentRule variable="k_P_R5">
        <math xmlns="http://www.w3.org/1998/Math/MathML">
          <cn> 6.8 </cn>
        </math>
      </assignmentRule>
      <assignmentRule variable="dG0_R5">
        <math xmlns="http://www.w3.org/1998/Math/MathML">
          <cn type="integer"> 4 </cn>
        </math>
      </assignmentRule>
      <assignmentRule variable="E_conc_R6">
        <math xmlns="http://www.w3.org/1998/Math/MathML">
          <cn type="integer"> 1 </cn>
        </math>
      </assignmentRule>
      <assignmentRule variable="k_cat_R6">
        <math xmlns="http://www.w3.org/1998/Math/MathML">
          <cn type="integer"> 24 </cn>
        </math>
      </assignmentRule>
      <assignmentRule variable="k_P_R6">
        <math xmlns="http://www.w3.org/1998/Math/MathML">
          <cn> 0.01 </cn>
        </math>
      </assignmentRule>
      <assignmentRule variable="k_Pex_R6">
        <math xmlns="http://www.w3.org/1998/Math/MathML">
          <cn type="integer"> 14 </cn>
        </math>
      </assignmentRule>
      <assignmentRule variable="dG0_R6">
        <math xmlns="http://www.w3.org/1998/Math/MathML">
          <cn type="integer"> 0 </cn>
        </math>
      </assignmentRule>
      <assignmentRule variable="E_conc_RTB">
        <math xmlns="http://www.w3.org/1998/Math/MathML">
          <cn type="integer"> 1 </cn>
        </math>
      </assignmentRule>
      <assignmentRule variable="k_cat_RTB">
        <math xmlns="http://www.w3.org/1998/Math/MathML">
          <cn type="integer"> 100000 </cn>
        </math>
      </assignmentRule>
      <assignmentRule variable="k_B_RTB">
        <math xmlns="http://www.w3.org/1998/Math/MathML">
          <cn type="integer"> 2 </cn>
        </math>
      </assignmentRule>
      <assignmentRule variable="k_Bex_RTB">
        <math xmlns="http://www.w3.org/1998/Math/MathML">
          <cn type="integer"> 2 </cn>
        </math>
      </assignmentRule>
      <assignmentRule variable="dG0_RTB">
        <math xmlns="http://www.w3.org/1998/Math/MathML">
          <cn type="integer"> 0 </cn>
        </math>
      </assignmentRule>
    </listOfRules>
    <listOfReactions>
      <reaction id="Sex_uptake" reversible="true" fast="false">
        <listOfProducts>
          <speciesReference species="Sex" stoichiometry="1" constant="true"/>
        </listOfProducts>
        <kineticLaw>
          <math xmlns="http://www.w3.org/1998/Math/MathML">
            <ci> Sex </ci>
          </math>
        </kineticLaw>
      </reaction>
      <reaction id="R1" reversible="true" fast="false">
        <listOfReactants>
          <speciesReference species="Sex" stoichiometry="1" constant="true"/>
        </listOfReactants>
        <listOfProducts>
          <speciesReference species="S" stoichiometry="1" constant="true"/>
        </listOfProducts>
        <kineticLaw>
          <math xmlns="http://www.w3.org/1998/Math/MathML">
            <apply>
              <ci> rate_law_one_s_one_p </ci>
              <ci> E_conc_R1 </ci>
              <ci> k_cat_R1 </ci>
              <ci> Sex </ci>
              <ci> S </ci>
              <ci> k_Sex_R1 </ci>
              <ci> k_S_R1 </ci>
              <ci> dG0_R1 </ci>
              <ci> R </ci>
              <ci> T </ci>
            </apply>
          </math>
        </kineticLaw>
      </reaction>
      <reaction id="R2" reversible="true" fast="false">
        <listOfReactants>
          <speciesReference species="S" stoichiometry="1" constant="true"/>
        </listOfReactants>
        <listOfProducts>
          <speciesReference species="A" stoichiometry="1" constant="true"/>
          <speciesReference species="X" stoichiometry="1" constant="true"/>
        </listOfProducts>
        <kineticLaw>
          <math xmlns="http://www.w3.org/1998/Math/MathML">
            <apply>
              <ci> rate_law_one_s_two_p </ci>
              <ci> E_conc_R2 </ci>
              <ci> k_cat_R2 </ci>
              <ci> S </ci>
              <ci> A </ci>
              <ci> X </ci>
              <ci> k_S_R2 </ci>
              <ci> k_A_R2 </ci>
              <ci> k_X_R2 </ci>
              <ci> dG0_R2 </ci>
              <ci> R </ci>
              <ci> T </ci>
            </apply>
          </math>
        </kineticLaw>
      </reaction>
      <reaction id="R3" reversible="true" fast="false">
        <listOfReactants>
          <speciesReference species="A" stoichiometry="1" constant="true"/>
          <speciesReference species="X" stoichiometry="1" constant="true"/>
        </listOfReactants>
        <listOfProducts>
          <speciesReference species="B" stoichiometry="1" constant="true"/>
        </listOfProducts>
        <kineticLaw>
          <math xmlns="http://www.w3.org/1998/Math/MathML">
            <apply>
              <ci> rate_law_two_s_one_p </ci>
              <ci> E_conc_R3 </ci>
              <ci> k_cat_R3 </ci>
              <ci> A </ci>
              <ci> X </ci>
              <ci> B </ci>
              <ci> k_A_R3 </ci>
              <ci> k_X_R3 </ci>
              <ci> k_B_R3 </ci>
              <ci> dG0_R3 </ci>
              <ci> R </ci>
              <ci> T </ci>
            </apply>
          </math>
        </kineticLaw>
      </reaction>
      <reaction id="R4" reversible="true" fast="false">
        <listOfReactants>
          <speciesReference species="B" stoichiometry="1" constant="true"/>
        </listOfReactants>
        <listOfProducts>
          <speciesReference species="C" stoichiometry="1" constant="true"/>
          <speciesReference species="X" stoichiometry="1" constant="true"/>
        </listOfProducts>
        <kineticLaw>
          <math xmlns="http://www.w3.org/1998/Math/MathML">
            <apply>
              <ci> rate_law_one_s_two_p </ci>
              <ci> E_conc_R4 </ci>
              <ci> k_cat_R4 </ci>
              <ci> B </ci>
              <ci> C </ci>
              <ci> X </ci>
              <ci> k_B_R4 </ci>
              <ci> k_C_R4 </ci>
              <ci> k_X_R4 </ci>
              <ci> dG0_R4 </ci>
              <ci> R </ci>
              <ci> T </ci>
            </apply>
          </math>
        </kineticLaw>
      </reaction>
      <reaction id="R5" reversible="true" fast="false">
        <listOfReactants>
          <speciesReference species="C" stoichiometry="1" constant="true"/>
          <speciesReference species="X" stoichiometry="1" constant="true"/>
        </listOfReactants>
        <listOfProducts>
          <speciesReference species="P" stoichiometry="1" constant="true"/>
        </listOfProducts>
        <kineticLaw>
          <math xmlns="http://www.w3.org/1998/Math/MathML">
            <apply>
              <ci> rate_law_two_s_one_p </ci>
              <ci> E_conc_R5 </ci>
              <ci> k_cat_R5 </ci>
              <ci> C </ci>
              <ci> X </ci>
              <ci> P </ci>
              <ci> k_C_R5 </ci>
              <ci> k_X_R5 </ci>
              <ci> k_P_R5 </ci>
              <ci> dG0_R5 </ci>
              <ci> R </ci>
              <ci> T </ci>
            </apply>
          </math>
        </kineticLaw>
      </reaction>
      <reaction id="R6" reversible="true" fast="false">
        <listOfReactants>
          <speciesReference species="P" stoichiometry="1" constant="true"/>
        </listOfReactants>
        <listOfProducts>
          <speciesReference species="Pex" stoichiometry="1" constant="true"/>
        </listOfProducts>
        <kineticLaw>
          <math xmlns="http://www.w3.org/1998/Math/MathML">
            <apply>
              <ci> rate_law_one_s_one_p </ci>
              <ci> E_conc_R6 </ci>
              <ci> k_cat_R6 </ci>
              <ci> P </ci>
              <ci> Pex </ci>
              <ci> k_P_R6 </ci>
              <ci> k_Pex_R6 </ci>
              <ci> dG0_R6 </ci>
              <ci> R </ci>
              <ci> T </ci>
            </apply>
          </math>
        </kineticLaw>
      </reaction>
      <reaction id="Pex_uptake" reversible="true" fast="false">
        <listOfReactants>
          <speciesReference species="Pex" stoichiometry="1" constant="true"/>
        </listOfReactants>
        <kineticLaw>
          <math xmlns="http://www.w3.org/1998/Math/MathML">
            <ci> Pex </ci>
          </math>
        </kineticLaw>
      </reaction>
      <reaction id="RTB" reversible="true" fast="false">
        <listOfReactants>
          <speciesReference species="B" stoichiometry="1" constant="true"/>
        </listOfReactants>
        <listOfProducts>
          <speciesReference species="Bex" stoichiometry="1" constant="true"/>
        </listOfProducts>
        <kineticLaw>
          <math xmlns="http://www.w3.org/1998/Math/MathML">
            <apply>
              <ci> rate_law_one_s_one_p </ci>
              <ci> E_conc_RTB </ci>
              <ci> k_cat_RTB </ci>
              <ci> B </ci>
              <ci> Bex </ci>
              <ci> k_B_RTB </ci>
              <ci> k_Bex_RTB </ci>
              <ci> dG0_RTB </ci>
              <ci> R </ci>
              <ci> T </ci>
            </apply>
          </math>
        </kineticLaw>
      </reaction>
    </listOfReactions>
  </model>
</sbml>
